taskiq_dashboard/__init__.py
taskiq_dashboard/api/__init__.py
taskiq_dashboard/api/__main__.py
taskiq_dashboard/api/application.py
taskiq_dashboard/api/middlewares.py
taskiq_dashboard/api/routers/__init__.py
taskiq_dashboard/api/routers/action.py
taskiq_dashboard/api/routers/event.py
taskiq_dashboard/api/routers/exception_handlers.py
taskiq_dashboard/api/routers/schedule.py
taskiq_dashboard/api/routers/system.py
taskiq_dashboard/api/routers/task.py
taskiq_dashboard/api/static/css/tailwind.css
taskiq_dashboard/api/static/favicon/favicon.ico
taskiq_dashboard/api/static/favicon/favicon.png
taskiq_dashboard/api/static/favicon/favicon.svg
taskiq_dashboard/api/static/htmx.js
taskiq_dashboard/api/static/icons/chevron-left.svg
taskiq_dashboard/api/static/icons/chevron-right.svg
taskiq_dashboard/api/static/icons/copy-check.svg
taskiq_dashboard/api/static/icons/copy.svg
taskiq_dashboard/api/static/icons/move-left.svg
taskiq_dashboard/api/static/icons.svg
taskiq_dashboard/api/static/logo_taskiq.svg
taskiq_dashboard/api/styles/main.css
taskiq_dashboard/api/templates/404.html
taskiq_dashboard/api/templates/home.html
taskiq_dashboard/api/templates/partial/head.html
taskiq_dashboard/api/templates/partial/header.html
taskiq_dashboard/api/templates/partial/notification.html
taskiq_dashboard/api/templates/partial/schedule_list.html
taskiq_dashboard/api/templates/partial/schedule_list_item.html
taskiq_dashboard/api/templates/partial/task_list.html
taskiq_dashboard/api/templates/partial/task_list_item.html
taskiq_dashboard/api/templates/schedule_details.html
taskiq_dashboard/api/templates/schedule_page.html
taskiq_dashboard/api/templates/scripts/copy-button.js
taskiq_dashboard/api/templates/scripts/focus_on_search_field.js
taskiq_dashboard/api/templates/task_details.html
taskiq_dashboard/api/templates.py
taskiq_dashboard/dependencies.py
taskiq_dashboard/domain/dto/__init__.py
taskiq_dashboard/domain/dto/task.py
taskiq_dashboard/domain/dto/task_status.py
taskiq_dashboard-0.3.2.dist-info/licenses/LICENSE
taskiq_dashboard-0.3.2.dist-info/WHEEL
taskiq_dashboard-0.3.2.dist-info/METADATA
taskiq_dashboard-0.3.2.dist-info/RECORD
