Metadata-Version: 2.4
Name: taskiq-dashboard
Version: 0.3.2
Summary: An interactive dashboard for monitoring and managing Taskiq tasks.
Keywords: taskiq,tasks,distributed,async,admin
Author: Anfimov Dima
Author-email: Anfimov Dima <lovesolaristics@gmail.com>
License-Expression: MIT
License-File: LICENSE
Classifier: Development Status :: 3 - Alpha
Classifier: Intended Audience :: Developers
Classifier: Intended Audience :: Information Technology
Classifier: Framework :: AsyncIO
Classifier: License :: OSI Approved :: MIT License
Classifier: Programming Language :: Python
Classifier: Programming Language :: Python :: 3
Classifier: Programming Language :: Python :: 3 :: Only
Classifier: Programming Language :: Python :: 3.10
Classifier: Programming Language :: Python :: 3.11
Classifier: Programming Language :: Python :: 3.12
Classifier: Programming Language :: Python :: 3.13
Classifier: Programming Language :: Python :: 3.14
Classifier: Programming Language :: Python :: Implementation :: CPython
Classifier: Topic :: Software Development :: Libraries :: Python Modules
Classifier: Topic :: Software Development :: Libraries
Classifier: Topic :: Software Development
Classifier: Topic :: System :: Networking
Classifier: Typing :: Typed
Classifier: Operating System :: OS Independent
Requires-Dist: fastapi>=0.120.0
Requires-Dist: uvicorn[standard]>=0.34.1
Requires-Dist: jinja2>=3.1.6
Requires-Dist: asyncpg>=0.30.0
Requires-Dist: sqlalchemy>=2.0.43
Requires-Dist: pydantic-settings>=2.11.0
Requires-Dist: dishka>=1.7.2
Requires-Dist: aiosqlite>=0.21.0
Requires-Dist: taskiq>=0.11.20
Requires-Python: >=3.10
Project-URL: Bug Tracker, https://github.com/danfimov/taskiq-dashboard/issues
Project-URL: Repository, https://github.com/danfimov/taskiq-dashboard/
